casbin_databases_adapter/__init__.py
casbin_databases_adapter/adapter.py
databases_casbin_adapter-0.0.1.dist-info/WHEEL
databases_casbin_adapter-0.0.1.dist-info/METADATA
databases_casbin_adapter-0.0.1.dist-info/RECORD
