Metadata-Version: 2.1
Name: databases-casbin-adapter
Version: 0.0.1
Summary: An adapter for PyCasbin that implemented by Databases library which support async process
License: MIT
Author: isasetiawan
Author-email: 10252610+isasetiawan@users.noreply.github.com
Requires-Python: >=3.8,<4.0
Classifier: License :: OSI Approved :: MIT License
Classifier: Programming Language :: Python :: 3
Classifier: Programming Language :: Python :: 3.8
Classifier: Programming Language :: Python :: 3.9
Classifier: Programming Language :: Python :: 3.10
Requires-Dist: SQLAlchemy (==1.4.46)
Requires-Dist: asynccasbin (==1.1.8)
Requires-Dist: databases (==0.7.0)
